{
  "name": "Ian Quinn",
  "age": 42,
  "address": {
    "street": "Ozogo Street",
    "city": "Rizvede",
    "state": "PA",
    "zip": "72578"
  },
  "contact": {
    "phone": "(472) 629-7763",
    "servicePhone": "800397898"
  },
  "birthday": "2004-08-19T04:30:29.351Z",
  "ip": "180.228.109.164",
  "foo": "bar",
  "profile": {
    "about": "Lupgo ga ef tauhe mib zog pulujsef dufnihnin ozfutoj dujwegpa tallolu lezdi urpo wicuvovov. Zi nojcazi ru fucuvfu uvahow dolwafhi ruviw sahlip iwpena rak fuppu mivcuj acihat nizcepid. Cisjimo ve enwi boupuek ne evogah footajo bakij wemer uvofo zujda ighassud pujef zecodof ifakuji. Asaelunu up vu azase jo zu fumrab hesnoki eltoito gujnobjam cedcejvef mak cad inov ritcehig cewnepsoc rancozec. Ecuwe wuwe goat ci pu zufom mi turofut zotewup ukpibnok zus sojjora tuwzivsa ri. Mufsiz faobuve nuljiviw wi hirof miskoj wam kaljo dezuh vurve rozidiz de becpa ju novjo. Vagaeda nun zuz pi mef len fanon ragwutga fufrilca jadmoh mefi womwi sesude ce ko kato so kisafdad.",
    "bio": "Divbu fe opmem ipmu jelejo vowazuv vez got nuje danlir pis zethiuv iwidon wesircan vo zi. Mevmusvu zimivbeb usuluje nojilo birdiwgo hev ijelen icialiat el goziduw if ugahakdu kocsiro awelulad muicse cijechic cohuc coligguz. Mi gepuvof fosiemu lunpuvvu nun lezguac wukpumbub febomja de ew hidos ol bilkawva pu. Luz rupegci sezilef miaze oru ice etpidlel vuwak iw maka fisjeb tuf ufe pojbokoc guviz avsaga vivojsen."
  },
  "apiKey": "76b18fd3c6d1aa047511f1e05323ed3640ab4e90cb48ed4ee3f845ee471db0ef",
  "currency": {
    "code": "PLN",
    "name": "Poland Zloty"
  }
}