{
  "name": "Lela Pratt",
  "age": 50,
  "address": {
    "street": "Awka Road",
    "city": "Jiotiteg",
    "state": "MT",
    "zip": "97363"
  },
  "contact": {
    "phone": "(771) 780-6120",
    "servicePhone": "800858836"
  },
  "birthday": "2005-03-27T16:20:33.604Z",
  "ip": "7.162.37.67",
  "foo": "bar",
  "profile": {
    "about": "Isvipgag gotas ir jutesun ko ranwupi ep ti cem jepavol fufu fetow owiza zones rijifez ve. Ori daric ban nu wios vekubpu pugjaki dabwuz ta hico mojloge kuwabko damcuw wihure izre kef kaztafpe if. Suw habjif tibbaupe gaokute tut vommar dor maradje uhotu lozawko waihse ko. Uwezitu gi sivice savaw corij ku akopimaj gopheko cittoclo wapgasew corsoj bilseb caucegen sap. Ah bup podeju bedolupu ga ej sos vupe ubina debem el hasekit vovohku faljejfuc ezo tu. Buc girotju oduopafu civlocjin bita nup hagu pizecaw hoz voh riromni roascem new. Robki pepanku pi go pu cimfid po bareegu tupehota obrejaj abe kipih cepne es.",
    "bio": "Gol lesuj wibin zezkal wipama nokkiw uzisac vugcos nuvu rik ubo hifwes fitkiog gepo pih seh. Veclomaf modrubiz oli uz wo casranul abumushi dive huzufo vap agi ijiva rewesjo lu de. Mi sidno vuegohaw bonaove gol wowed mefdav renman nuswis idji avcu eriref suw. Pew pocceop ora ho zukeoce kodocnan hem niliobo ziwbesim few piwaan hudzajhe fad voefeha zizvu da."
  },
  "apiKey": "b69c521f9fb50384a742065c2e17b98659318a9bcec8dec95e7d6b3ae1a24b3c",
  "currency": {
    "code": "AFN",
    "name": "Afghanistan Afghani"
  }
}